NMR/__init__.py
NMR/admin.py
NMR/apps.py
NMR/models.py
NMR/nn.py
NMR/process.py
NMR/svm.py
NMR/tests.py
NMR/urls.py
NMR/validators.py
NMR/views.py
nmrglue/__init__.py
nmrglue/analysis/__init__.py
nmrglue/analysis/analysisbase.py
nmrglue/analysis/helpers.py
nmrglue/analysis/integration.py
nmrglue/analysis/leastsqbound.py
nmrglue/analysis/linesh.py
nmrglue/analysis/lineshapes1d.py
nmrglue/analysis/peakpick.py
nmrglue/analysis/segmentation.py
nmrglue/analysis/tests/test_analysis_integration.py
nmrglue/analysis/tests/test_analysis_linesh.py
nmrglue/fileio/__init__.py
nmrglue/fileio/bruker.py
nmrglue/fileio/convert.py
nmrglue/fileio/fileiobase.py
nmrglue/fileio/glue.py
nmrglue/fileio/jcampdx.py
nmrglue/fileio/nmrml.py
nmrglue/fileio/pipe.py
nmrglue/fileio/rnmrtk.py
nmrglue/fileio/simpson.py
nmrglue/fileio/sparky.py
nmrglue/fileio/table.py
nmrglue/fileio/tecmag.py
nmrglue/fileio/varian.py
nmrglue/fileio/tests/test_bruker.py
nmrglue/fileio/tests/test_fileiobase.py
nmrglue/fileio/tests/test_pipe.py
nmrglue/process/__init__.py
nmrglue/process/pipe_proc.py
nmrglue/process/proc_autophase.py
nmrglue/process/proc_base.py
nmrglue/process/proc_bl.py
nmrglue/process/proc_lp.py
nmrglue/process/nmrtxt/__init__.py
nmrglue/process/nmrtxt/rance_kay.py
nmrglue/util/__init__.py
nmrglue/util/misc.py
NMR_peaks_picking-0.1.dist-info/LICENSE
NMR_peaks_picking-0.1.dist-info/METADATA
NMR_peaks_picking-0.1.dist-info/WHEEL
NMR_peaks_picking-0.1.dist-info/top_level.txt
NMR_peaks_picking-0.1.dist-info/RECORD
