Metadata-Version: 2.1
Name: NMR-peaks-picking
Version: 0.1
Summary: UNKNOWN
Home-page: https://github.com/ChinyaChao/NMR-peaks-picking-website
Author: Chinya Chao
Author-email: C.Chao@liverpool.ac.uk
License: MIT
Platform: UNKNOWN
Requires-Dist: Django (==2.2.5)
Requires-Dist: django-cleanup (==4.0.0)
Requires-Dist: imageio (==2.5.0)
Requires-Dist: matplotlib (==3.1.1)
Requires-Dist: nmrglue (==0.7)
Requires-Dist: numpy (==1.17.1)
Requires-Dist: Pillow (==6.1.0)
Requires-Dist: scikit-image (==0.15.0)
Requires-Dist: scikit-learn (==0.21.3)
Requires-Dist: scipy (==1.3.1)
